{"image":{"image_id":795,"license":1,"file_name":"Cat17_1_jpg.rf.2beb57a9e83db5d54d7bef3bf4c8593b.jpg","height":1080,"width":1080,"date_captured":"2024-10-05T09:44:39+00:00"},"annotations":[{"id":6879,"bbox":[577,15,376.7985,353.200501],"area":133085.41897604847,"segmentation":{"counts":"0Q^a01hm^OOV:1jEOV:1jEOV:1jEOV:1jEOV:1jEOV:1jEOV:1jEOV:1jEOV:1jEOV:1jEOV:1jEOV:1jEOV:1jEOV:1jEOV:1jEOV:1jEOV:1jEOV:1jEOV:1jEOV:1jEOV:1jEOV:1jEOV:1jEOV:1jEOV:1jEOV:1jEOV:1jEOV:1jEOV:1jEOV:1jEOV:1jEOV:1jEOV:1jEOV:1jEOV:1jEOV:1jEOV:1jEOV:1jEOV:1jEOV:1jEOV:1jEOV:1jEOV:1jEOV:1jEOV:1jEOV:1jEOV:1jEOV:1jEOV:1jEOV:1jEOV:1jEOV:1jEOV:1jEOV:1jEOV:1jEOV:1jEOV:1jEOV:1jEOV:1jEOV:1jEOV:1jEOV:1jEOV:1jEOV:1jEOV:1jEOV:1jEOV:1jEOV:1jEOV:1jEOV:1jEOV:1jEOV:1jEOV:1jEOV:1jEOV:1jEOV:1jEOV:1jEOV:1jEOV:1jEOV:1jEOV:1jEOV:1jEOV:1jEOV:1jEOV:1jEOV:1jEOV:1jEOV:1jEOV:1jEOV:1jEOV:1jEOV:1jEOV:1jEOV:1jEOV:1jEOV:1jEOV:1jEOV:1jEOV:1jEOV:1jEOV:1jEOV:1jEOV:1jEOV:1jEOV:1jEOV:1jEOV:1jEOV:1jEOV:1jEOV:1jEOV:1jEOV:1jEOV:1jEOV:1jEOV:1jEOV:1jEOV:1jEOV:1jEOV:1jEOV:1jEOV:1jEOV:1jEOV:1jEOV:1jEOV:1jEOV:1jEOV:1jEOV:1jEOV:1jEOV:1jEOV:1jEOV:1jEOV:1jEOV:1jEOV:1jEOV:1jEOV:1jEOV:1jEOV:1jEOV:1jEOV:1jEOV:1jEOV:1jEOV:1jEOV:1jEOV:1jEOV:1jEOV:1jEOV:1jEOV:1jEOV:1jEOV:1jEOV:1jEOV:1jEOV:1jEOV:1jEOV:1jEOV:1jEOV:1jEOV:1jEOV:1jEOV:1jEOV:1jEOV:1jEOV:1jEOV:1jEOV:1jEOV:1jEOV:1jEOV:1jEOV:1jEOV:1jEOV:1jEOV:1jEOV:1jEOV:1jEOV:1jEOV:1jEOV:1jEOV:1jEOV:1jEOV:1jEOV:1jEOV:1jEOV:1jEOV:1jEOV:1jEOV:1jEOV:1jEOV:1jEOV:1jEOV:1jEOV:1jEOV:1jEOV:1jEOV:1jEOV:1jEOV:1jEOV:1jEOV:1jEOV:1jEOV:1jEOV:1jEOV:1jEOV:1jEOV:1jEOV:1jEOV:1jEOV:1jEOV:1jEOV:1jEOV:1jEOV:1jEOV:1jEOV:1jEOV:1jEOV:1jEOV:1jEOV:1jEOV:1jEOV:1jEOV:1jEOV:1jEOV:1jEOV:1jEOV:1jEOV:1jEOV:1jEOV:1jEOV:1jEOV:1jEOV:1jEOV:1jEOV:1jEOV:1jEOV:1jEOV:1jEOV:1jEOV:1jEOV:1jEOV:1jEOV:1jEOV:1jEOV:1jEOV:1jEOV:1jEOV:1jEOV:1jEOV:1jEOV:1jEOV:1jEOV:1jEOV:1jEOV:1jEOV:1jEOV:1jEOV:1jEOV:1jEOV:1jEOV:1jEOV:1jEOV:1jEOV:1jEOV:1jEOV:1jEOV:1jEOV:1jEOV:1jEOV:1jEOV:1jEOV:1jEOV:1jEOV:1jEOV:1jEOV:1jEOV:1jEOV:1jEOV:1jEOV:1jEOV:1jEOV:1jEOV:1jEOV:1jEOV:1jEOV:1jEOV:1jEOV:1jEOV:1jEOV:1jEOV:1jEOV:1jEOV:1jEOV:1jEOV:1jEOV:1jEOV:1jEOV:1jEOV:1jEOV:1jEOV:1jEOV:1jEOV:1jEOV:1jEOV:1jEOV:1jEOV:1jEOV:1jEOV:1jEOV:1jEOV:1jEOV:1jEOV:1jEOV:1jEOV:1jEOV:1jEOV:1jEOV:1jEOV:1jEOV:1jEOV:1jEOV:1jEOV:1jEOV:1jEOV:1jEOV:1jEOV:1jEOV:1jEOV:1jEOV:1jEOV:1jEOV:1jEOV:1jEOV:1jEOV:1jEOV:1jEOV:1jEOV:1jEOV:1jEOV:1jEOV:1jEOV:1jEOV:1jEOV:1jEOV:1jEOV:1jEOV:1jEOV:1jEOV:1jEOV:1jEOV:1jEOV:1jEOV:1jEO]d]g0","size":[1080,1080]}},{"id":6880,"bbox":[389,384,564.639187,405.57712499999997],"area":229004.73812579736,"segmentation":{"counts":"0U\\e<1TiZCOg61\\DOg?1b1O^N1b1O^N1b1O^N1b1O^N1b1O^N1b1O^N1b1O^N1b1O^N1b1O^N1b1O^N1b1O^N1b1O^N1b1O^N1b1O^N1b1O^N1b1O^N1b1O^N1b1O^N1b1O^N1b1O^N1b1O^N1b1O^N1b1O^N1b1O^N1b1O^N1b1O^N1b1O^N1b1O^N1b1O^N1b1O^N1b1O^N1b1O^N1b1O^N1b1O^N1b1O^N1b1O^N1b1O^N1b1O^N1b1O^N1b1O^N1b1O^N1b1O^N1b1O^N1b1O^N1b1O^N1b1O^N1b1O^N1b1O^N1b1O^N1b1O^N1b1O^N1b1O^N1b1O^N1b1O^N1b1O^N1b1O^N1b1O^N1b1O^N1b1O^N1b1O^N1b1O^N1b1O^N1b1O^N1b1O^N1b1O^N1b1O^N1b1O^N1b1O^N1b1O^N1b1O^N1b1O^N1b1O^N1b1O^N1b1O^N1b1O^N1b1O^N1b1O^N1b1O^N1b1O^N1b1O^N1b1O^N1b1O^N1b1O^N1b1O^N1b1O^N1b1O^N1b1O^N1b1O^N1b1O^N1b1O^N1b1O^N1b1O^N1b1O^N1b1O^N1b1O^N1b1O^N1b1O^N1b1O^N1b1O^N1b1O^N1b1O^N1b1O^N1b1O^N1b1O^N1b1O^N1b1O^N1b1O^N1b1O^N1b1O^N1b1O^N1b1O^N1b1O^N1b1O^N1b1O^N1b1O^N1b1O^N1b1O^N1b1O^N1b1O^N1b1O^N1b1O^N1b1O^N1b1O^N1b1O^N1b1O^N1b1O^N1b1O^N1b1O^N1b1O^N1b1O^N1b1O^N1b1O^N1b1O^N1b1O^N1b1O^N1b1O^N1b1O^N1b1O^N1b1O^N1b1O^N1b1O^N1b1O^N1b1O^N1b1O^N1b1O^N1b1O^N1b1O^N1b1O^N1b1O^N1b1O^N1b1O^N1b1O^N1b1O^N1b1O^N1b1O^N1b1O^N1b1O^N1b1O^N1b1O^N1b1O^N1b1O^N1b1O^N1b1O^N1b1O^N1b1O^N1b1O^N1b1O^N1b1O^N1b1O^N1b1O^N1b1O^N1b1O^N1b1O^N1b1O^N1b1O^N1b1O^N1b1O^N1b1O^N1b1O^N1b1O^N1b1O^N1b1O^N1b1O^N1b1O^N1b1O^N1b1O^N1b1O^N1b1O^N1b1O^N1b1O^N1b1O^N1b1O^N1b1O^N1b1O^N1b1O^N1b1O^N1b1O^N1b1O^N1b1O^N1b1O^N1b1O^N1b1O^N1b1O^N1b1O^N1b1O^N1b1O^N1b1O^N1b1O^N1b1O^N1b1O^N1b1O^N1b1O^N1b1O^N1b1O^N1b1O^N1b1O^N1b1O^N1b1O^N1b1O^N1b1O^N1b1O^N1b1O^N1b1O^N1b1O^N1b1O^N1b1O^N1b1O^N1b1O^N1b1O^N1b1O^N1b1O^N1b1O^N1b1O^N1b1O^N1b1O^N1b1O^N1b1O^N1b1O^N1b1O^N1b1O^N1b1O^N1b1O^N1b1O^N1b1O^N1b1O^N1b1O^N1b1O^N1b1O^N1b1O^N1b1O^N1b1O^N1b1O^N1b1O^N1b1O^N1b1O^N1b1O^N1b1O^N1b1O^N1b1O^N1b1O^N1b1O^N1b1O^N1b1O^N1b1O^N1b1O^N1b1O^N1b1O^N1b1O^N1b1O^N1b1O^N1b1O^N1b1O^N1b1O^N1b1O^N1b1O^N1b1O^N1b1O^N1b1O^N1b1O^N1b1O^N1b1O^N1b1O^N1b1O^N1b1O^N1b1O^N1b1O^N1b1O^N1b1O^N1b1O^N1b1O^N1b1O^N1b1O^N1b1O^N1b1O^N1b1O^N1b1O^N1b1O^N1b1O^N1b1O^N1b1O^N1b1O^N1b1O^N1b1O^N1b1O^N1b1O^N1b1O^N1b1O^N1b1O^N1b1O^N1b1O^N1b1O^N1b1O^N1b1O^N1b1O^N1b1O^N1b1O^N1b1O^N1b1O^N1b1O^N1b1O^N1b1O^N1b1O^N1b1O^N1b1O^N1b1O^N1b1O^N1b1O^N1b1O^N1b1O^N1b1O^N1b1O^N1b1O^N1b1O^N1b1O^N1b1O^N1b1O^N1b1O^N1b1O^N1b1O^N1b1O^N1b1O^N1b1O^N1b1O^N1b1O^N1b1O^N1b1O^N1b1O^N1b1O^N1b1O^N1b1O^N1b1O^N1b1O^N1b1O^N1b1O^N1b1O^N1b1O^N1b1O^N1b1O^N1b1O^N1b1O^N1b1O^N1b1O^N1b1O^N1b1O^N1b1O^N1b1O^N1b1O^N1b1O^N1b1O^N1b1O^N1b1O^N1b1O^N1b1O^N1b1O^N1b1O^N1b1O^N1b1O^N1b1O^N1b1O^N1b1O^N1b1O^N1b1O^N1b1O^N1b1O^N1b1O^N1b1O^N1b1O^N1b1O^N1b1O^N1b1O^N1b1O^N1b1O^N1b1O^N1b1O^N1b1O^N1b1O^N1b1O^N1b1O^N1b1O^N1b1O^N1b1O^N1b1O^N1b1O^N1b1O^N1b1Oi]a9","size":[1080,1080]}},{"id":6881,"bbox":[15,384,358.25793799999997,680.697],"area":243865.10362278597,"segmentation":{"counts":"0`Pe<1RS[COdj01P]OO\\;1dDO\\;1dDO\\;1dDO\\;1dDO\\;1dDO\\;1dDO\\;1dDO\\;1dDO\\;1dDO\\;1dDO\\;1dDO\\;1dDO\\;1dDO\\;1dDO\\;1dDO\\;1dDO\\;1dDO\\;1dDO\\;1dDO\\;1dDO\\;1dDO\\;1dDO\\;1dDO\\;1dDO\\;1dDO\\;1dDO\\;1dDO\\;1dDO\\;1dDO\\;1dDO\\;1dDO\\;1dDO\\;1dDO\\;1dDO\\;1dDO\\;1dDO\\;1dDO\\;1dDO\\;1dDO\\;1dDO\\;1dDO\\;1dDO\\;1dDO\\;1dDO\\;1dDO\\;1dDO\\;1dDO\\;1dDO\\;1dDO\\;1dDO\\;1dDO\\;1dDO\\;1dDO\\;1dDO\\;1dDO\\;1dDO\\;1dDO\\;1dDO\\;1dDO\\;1dDO\\;1dDO\\;1dDO\\;1dDO\\;1dDO\\;1dDO\\;1dDO\\;1dDO\\;1dDO\\;1dDO\\;1dDO\\;1dDO\\;1dDO\\;1dDO\\;1dDO\\;1dDO\\;1dDO\\;1dDO\\;1dDO\\;1dDO\\;1dDO\\;1dDO\\;1dDO\\;1dDO\\;1dDO\\;1dDO\\;1dDO\\;1dDO\\;1dDO\\;1dDO\\;1dDO\\;1dDO\\;1dDO\\;1dDO\\;1dDO\\;1dDO\\;1dDO\\;1dDO\\;1dDO\\;1dDO\\;1dDO\\;1dDO\\;1dDO\\;1dDO\\;1dDO\\;1dDO\\;1dDO\\;1dDO\\;1dDO\\;1dDO\\;1dDO\\;1dDO\\;1dDO\\;1dDO\\;1dDO\\;1dDO\\;1dDO\\;1dDO\\;1dDO\\;1dDO\\;1dDO\\;1dDO\\;1dDO\\;1dDO\\;1dDO\\;1dDO\\;1dDO\\;1dDO\\;1dDO\\;1dDO\\;1dDO\\;1dDO\\;1dDO\\;1dDO\\;1dDO\\;1dDO\\;1dDO\\;1dDO\\;1dDO\\;1dDO\\;1dDO\\;1dDO\\;1dDO\\;1dDO\\;1dDO\\;1dDO\\;1dDO\\;1dDO\\;1dDO\\;1dDO\\;1dDO\\;1dDO\\;1dDO\\;1dDO\\;1dDO\\;1dDO\\;1dDO\\;1dDO\\;1dDO\\;1dDO\\;1dDO\\;1dDO\\;1dDO\\;1dDO\\;1dDO\\;1dDO\\;1dDO\\;1dDO\\;1dDO\\;1dDO\\;1dDO\\;1dDO\\;1dDO\\;1dDO\\;1dDO\\;1dDO\\;1dDO\\;1dDO\\;1dDO\\;1dDO\\;1dDO\\;1dDO\\;1dDO\\;1dDO\\;1dDO\\;1dDO\\;1dDO\\;1dDO\\;1dDO\\;1dDO\\;1dDO\\;1dDO\\;1dDO\\;1dDO\\;1dDO\\;1dDO\\;1dDO\\;1dDO\\;1dDO\\;1dDO\\;1dDO\\;1dDO\\;1dDO\\;1dDO\\;1dDO\\;1dDO\\;1dDO\\;1dDO\\;1dDO\\;1dDO\\;1dDO\\;1dDO\\;1dDO\\;1dDO\\;1dDO\\;1dDO\\;1dDO\\;1dDO\\;1dDO\\;1dDO\\;1dDO\\;1dDO\\;1dDO\\;1dDO\\;1dDO\\;1dDO\\;1dDO\\;1dDO\\;1dDO\\;1dDO\\;1dDO\\;1dDO\\;1dDO\\;1dDO\\;1dDO\\;1dDO\\;1dDO\\;1dDO\\;1dDO\\;1dDO\\;1dDO\\;1dDO\\;1dDO\\;1dDO\\;1dDO\\;1dDO\\;1dDO\\;1dDO\\;1dDO\\;1dDO\\;1dDO\\;1dDO\\;1dDO\\;1dDO\\;1dDO\\;1dDO\\;1dDO\\;1dDO\\;1dDO\\;1dDO\\;1dDO\\;1dDO\\;1dDO\\;1dDO\\;1dDO\\;1dDO\\;1dDO\\;1dDO\\;1dDO\\;1dDO\\;1dDO\\;1dDO\\;1dDO\\;1dDO\\;1dDO\\;1dDO\\;1dDO\\;1dDO\\;1dDO\\;1dDO\\;1dDO\\;1dDO\\;1dDO\\;1dDO\\;1dDO\\;1dDO\\;1dDO\\;1dDO\\;1dDO\\;1dDO\\;1dDO\\;1dDO\\;1dDO\\;1dDO\\;1dDO\\;1dDO\\;1dDO\\;1dDO\\;1dDO\\;1dDO\\;1dDO\\;1dDO\\;1dDO\\;1dDO\\;1dDO\\;1dDO\\;1dDO\\;1dDO\\;1dDO\\;1dDO\\;1dDO\\;1dDO\\;1dDO\\;1dDO\\;1dDO\\;1dDO\\;1dDO\\;1dDO\\;1dDO\\;1dDO\\;1dDO\\;1dDO\\;1dDO\\;1dDO\\;1dDO\\;1dDO\\;1dDO\\;1dDO\\;1dDO\\;1dDO\\;1dDO\\;1dDO\\;1dDO\\;1dDO\\;1dDO\\;1dDO\\;1dDO\\;1dDO\\;1dDO\\;1dDO\\;1dDO\\;1dDO\\;1dDO\\;1dDO\\;1dDO\\;1dDO\\;1dDO\\;1dDO\\;1dDO\\;1dDO\\;1dDO\\;1dDO\\;1dDO\\;1dDO\\;1dDO\\;1dDO\\;1dDO\\;1dDO\\;1dDO\\;1dDO\\;1dDO\\;1dDO\\;1dDO\\;1dDO\\;1dDO\\;1dDO\\;1dDO\\;1dDO\\;1dDO\\;1dDO\\;1dDO\\;1dDO\\;1dDO\\;1dDO\\;1dDO\\;1dDO\\;1dDO\\;1dDO\\;1dDO\\;1dDO\\;1dDO\\;1dDO\\;1dDO\\;1dDO\\;1dDO\\;1dDO\\;1dDO\\;1dDO\\;1dDO\\;1dDO\\;1dDO\\;1dDO\\;1dDO\\;1dDO\\;1dDO\\;1dDO\\;1dDO\\;1dDO\\;1dDO\\;1dDO\\;1dDO\\;1dDO\\;1dDO\\;1dDO\\;1dDO\\;1dDO\\;1PAOdb01\\]OOdb01\\]OOdb01\\]OOdb01\\]OOdb01\\]OOdb01\\]OOdb01\\]OOdb01\\]OOdb01\\]OOdb01\\]OOdb01\\]OOdb01\\]OOdb01\\]OOdb01\\]OOdb01\\]OOdb01\\]OOdb01\\]OOdb01\\]OOdb01\\]OOdb01\\]OOdb01\\]OOdb01\\]OOdb01\\]OOdb01\\]OOdb01\\]OOdb01\\]OOdb01\\]OOdb01\\]OOdb01\\]OOdb01\\]OOdb01\\]OOdb01\\]OOdb01\\]OOdb01\\]OOdb01\\]OOdb01\\]OOdb01\\]OOdb01\\]OOdb01\\]OOdb01\\]OOdb01\\]OOdb01\\]OOdb01\\]OOdb01\\]OOdb01\\]OOdb01\\]OOdb01\\]OOdb01\\]OOdb01\\]OOdb01\\]OOdb01\\]OOdb01\\]OOdb01\\]OOdb01\\]OOdb01\\]OOdb01\\]OOdb01\\]OOdb01\\]OOdb01\\]OOdb01\\]OOdb01\\]OOdb01\\]OOdb01\\]OOdb01\\]OOdb01\\]OOdb01\\]OOdb01\\]OOdb01\\]OOdb01\\]OOdb01\\]OOdb01\\]OOdb01\\]OOdb01\\]OOdb01\\]OOdb01\\]OOdb01\\]OOdb01\\]OOdb01\\]OOdb01\\]OOdb01\\]OOdb01\\]OOdb01\\]OOdb01\\]OOdb01\\]OOdb01\\]OOdb01\\]OOdb01\\]OOdb01\\]OOdb01\\]OOdb01\\]OOdb01\\]OOdb01\\]OOdb01\\]OOdb01\\]OOdb01\\]OOdb01\\]OOdb01\\]OOdb01\\]OOdb01\\]OOdb01\\]OOdb01\\]OOdb01\\]OOdb01\\]OOdb01\\]OOdb01\\]OOdb01\\]OOdb01\\]OOdb01\\]OOdb01\\]OOdb01\\]OOdb01\\]OOdb01\\]OOdb01\\]OOdb01\\]OOdb01\\]OOdb01\\]OOdb01\\]OOdb01\\]OOdb01\\]OOdb01\\]OOdb01\\]OOdb01\\]OOdb01\\]OOdb01\\]OOdb01\\]OOdb01\\]OOdb01\\]OOdb01\\]OOdb01\\]OOdb01\\]OOdb01\\]OOdb01\\]OOdb01\\]OOdb01\\]OOdb01\\]OOdb01\\]OOdb01\\]OOdb01\\]OOdb01\\]OOdb01\\]OOdb01\\]OOdb01\\]OOdb01\\]OOdb01\\]OOdb01\\]OOdb01\\]OOdb01\\]OOdb01\\]OOdb01\\]OOdb01\\]OOdb01\\]OOdb01\\]OOdb01\\]OOdb01\\]OOdb01\\]OOdb01\\]OOdb01\\]OOdb01\\]OOdb01\\]OOdb01\\]OOdb01\\]OOdb01\\]OOdb01\\]OOdb01\\]OOdb01\\]OOdb01\\]OOdb01\\]OOdb01\\]OOdb01\\]OOdb01\\]OOdb01\\]OOdb01\\]OOdb01\\]OOdb01\\]OOdb01\\]OOdb01\\]OOdb01\\]OOdb01\\]OOdb01\\]OOdb01\\]OOdb01\\]OOdb01\\]OOdb01\\]OOdb01\\]OOdb01\\]OOdb01\\]OOdb01\\]OOdb01\\]OOdb01\\]OOdb01\\]OOdb01\\]OOdb01\\]OOdb01\\]OOdb01\\]OOdb01\\]OOdb01\\]OOdb01\\]OOdb01\\]OOdb01\\]OOdb01\\]OOdb01\\]OOdb01\\]OOdb01\\]OOdb01\\]OOdb01\\]OOdb01\\]OOdb01\\]OOdb01\\]OOdb01\\]OOdb01\\]OOdb01\\]OOdb01\\]OOdb01\\]OOdb01\\]OOdb01\\]OOdb01\\]OOdb01\\]OOdb01\\]OOdb01\\]OOdb01\\]OOdb01\\]OOdb01\\]OOdb01\\]OOdb01\\]OOdb01\\]OOdb01\\]OOdb01\\]OOdb01\\]OOdb01\\]OOdb01\\]OOdb01\\]OOdb01\\]OOdb01\\]OOdb01\\]OOdb01\\]OOdb01\\]OOdb01\\]OOdb01\\]OOdb01\\]OOdb01\\]OOdb01\\]OOdb01\\]OOdb01\\]OOdb01\\]OOdb01\\]OOdb01\\]OOdb01\\]OOdb01\\]OOdb01\\]OOdb01\\]OOdb01\\]OOdb01\\]OOdb01\\]OOdb01\\]OOdb01\\]OOdb01\\]OOdb01\\]OOdb01\\]OOdb01\\]OOdb01\\]OOdb01\\]OOdb01\\]OOdb01\\]OOdb01\\]OOdb01\\]OOdb01\\]OOdb01\\]OOdb01\\]OOdb01\\]OOdb01\\]OOdb01\\]OOdb01\\]OOdb01\\]OO\\\\`0","size":[1080,1080]}}]}